LICENSE.txt
MANIFEST.in
README.md
requirements.txt
setup.cfg
setup.py
consullock/__init__.py
consullock/_helpers.py
consullock/_logging.py
consullock/cli.py
consullock/configuration.py
consullock/exceptions.py
consullock/json_mappers.py
consullock/managers.py
consullock/models.py
consullock.egg-info/PKG-INFO
consullock.egg-info/SOURCES.txt
consullock.egg-info/dependency_links.txt
consullock.egg-info/entry_points.txt
consullock.egg-info/requires.txt
consullock.egg-info/top_level.txt
consullock.egg-info/zip-safe
consullock/tests/__init__.py
consullock/tests/_common.py
consullock/tests/_test_locks.py
consullock/tests/test_cli.py
consullock/tests/test_managers.py