Metadata-Version: 1.0
Name: consullock
Version: 4.2.0
Summary: Tool to use locks in Consul
Home-page: https://github.com/wtsi-hgi/consul-lock
Author: UNKNOWN
Author-email: UNKNOWN
License: MIT
Platform: UNKNOWN
